{
    "name": "Koi Thé Café - Saigon Garden",
    "link": "https://www.foody.vn/ho-chi-minh/koi-the-cafe-viet-nam-saigon-garden",
    "address": "108-110 Hồ Tùng Mậu, P. Bến Nghé,  Quận 1, TP. HCM",
    "open_time": "10:00 AM - 10:00 PM",
    "price_range": "40.000đ - 60.000đ",
    "category": [
        {
            "category": "Café/Dessert",
            "link": "https://www.foody.vn/ho-chi-minh/food/cafe"
        },
        {
            "category": "Singapore",
            "link": "https://www.foody.vn/ho-chi-minh/cafe-phong-cach-singapore"
        },
        {
            "category": "Chi nhánh",
            "link": "https://www.foody.vn/thuong-hieu/koi-the-cafe-viet-nam?c=ho-chi-minh"
        }
    ],
    "values": [
        {
            "label": "Chất lượng",
            "score": "7.9"
        },
        {
            "label": "Vị trí",
            "score": "7.9"
        },
        {
            "label": "Không gian",
            "score": "7.7"
        },
        {
            "label": "Phục vụ",
            "score": "7.4"
        },
        {
            "label": "Giá cả",
            "score": "6.7"
        }
    ],
    "summary": {
        "average_score": "7.5",
        "total_review": "220"
    },
    "foods": [
        {
            "name": "Matcha Latte (S)",
            "price": "48,000(đ)",
            "total_orders": "5843"
        },
        {
            "name": "Matcha Latte (M)",
            "price": "66,000(đ)",
            "total_orders": "2259"
        },
        {
            "name": "Black Tea Latte (S)",
            "price": "42,000(đ)",
            "total_orders": "1645"
        },
        {
            "name": "Black Tea Latte (M)",
            "price": "59,000(đ)",
            "total_orders": "1162"
        },
        {
            "name": "Ovaltine Latte (S)",
            "price": "48,000(đ)",
            "total_orders": "1077"
        },
        {
            "name": "Green Tea Latte (S)",
            "price": "42,000(đ)",
            "total_orders": "869"
        },
        {
            "name": "Ovaltine Latte (M)",
            "price": "66,000(đ)",
            "total_orders": "710"
        },
        {
            "name": "Green Tea Latte (M)",
            "price": "59,000(đ)",
            "total_orders": "692"
        },
        {
            "name": "Black tea macchiato - Hồng trà macchiato (S)",
            "price": "39,000(đ)",
            "total_orders": "43493"
        },
        {
            "name": "Black tea macchiato - Hồng trà macchiato (M)",
            "price": "55,000(đ)",
            "total_orders": "20104"
        },
        {
            "name": "Green tea macchiato - Lục trà macchiato (S)",
            "price": "39,000(đ)",
            "total_orders": "14649"
        },
        {
            "name": "Peach macchiato - Mứt đào macchiato (S)",
            "price": "48,000(đ)",
            "total_orders": "13169"
        },
        {
            "name": "Ovaltine macchiato - Cacao macchiato (S)",
            "price": "50,000(đ)",
            "total_orders": "8460"
        },
        {
            "name": "Mango macchiato - Mứt xoài macchiato (S)",
            "price": "48,000(đ)",
            "total_orders": "8459"
        },
        {
            "name": "Green tea macchiato - Lục trà macchiato (M)",
            "price": "55,000(đ)",
            "total_orders": "7139"
        },
        {
            "name": "Matcha macchiato - Trà xanh macchiato (S)",
            "price": "50,000(đ)",
            "total_orders": "6635"
        },
        {
            "name": "Peach macchiato - Mứt đào macchiato (M)",
            "price": "66,000(đ)",
            "total_orders": "5005"
        },
        {
            "name": "Passion fruit macchiato - Chanh dây macchiato (S)",
            "price": "48,000(đ)",
            "total_orders": "4465"
        },
        {
            "name": "Ovaltine macchiato - Cacao macchiato (M)",
            "price": "70,000(đ)",
            "total_orders": "3755"
        },
        {
            "name": "Mango macchiato - Mứt xoài macchiato (M)",
            "price": "66,000(đ)",
            "total_orders": "3429"
        },
        {
            "name": "Matcha macchiato - Trà xanh macchiato (M)",
            "price": "70,000(đ)",
            "total_orders": "3401"
        },
        {
            "name": "Hazelnut macchiato - Trà hạt phỉ macchiato (S)",
            "price": "42,000(đ)",
            "total_orders": "3011"
        },
        {
            "name": "Passion fruit macchiato - Chanh dây macchiato (M)",
            "price": "66,000(đ)",
            "total_orders": "2035"
        },
        {
            "name": "Hazelnut macchiato - Trà hạt phỉ macchiato (M)",
            "price": "60,000(đ)",
            "total_orders": "1184"
        },
        {
            "name": "Lục trà mật ong (S)",
            "price": "37,000(đ)",
            "total_orders": "6419"
        },
        {
            "name": "Lục trà đào (S)",
            "price": "37,000(đ)",
            "total_orders": "5524"
        },
        {
            "name": "Lục trà lài (S)",
            "price": "29,000(đ)",
            "total_orders": "3686"
        },
        {
            "name": "Assam hồng trà (S)",
            "price": "29,000(đ)",
            "total_orders": "3422"
        },
        {
            "name": "Lục trà chanh tươi (S)",
            "price": "37,000(đ)",
            "total_orders": "2733"
        },
        {
            "name": "Lục trà mật ong (M)",
            "price": "52,000(đ)",
            "total_orders": "2219"
        },
        {
            "name": "Lục trà chanh dây (S)",
            "price": "37,000(đ)",
            "total_orders": "2207"
        },
        {
            "name": "Lục trà xoài (S)",
            "price": "37,000(đ)",
            "total_orders": "1859"
        },
        {
            "name": "Assam hồng trà (M)",
            "price": "41,000(đ)",
            "total_orders": "1742"
        },
        {
            "name": "Lục trà đào (M)",
            "price": "52,000(đ)",
            "total_orders": "1442"
        },
        {
            "name": "Lục trà lài (M)",
            "price": "41,000(đ)",
            "total_orders": "1359"
        },
        {
            "name": "Lục trà chanh dây (M)",
            "price": "52,000(đ)",
            "total_orders": "1009"
        },
        {
            "name": "Lục trà chanh tươi (M)",
            "price": "52,000(đ)",
            "total_orders": "774"
        },
        {
            "name": "Lục trà xoài (M)",
            "price": "52,000(đ)",
            "total_orders": "728"
        },
        {
            "name": "Lục trà sữa (S)",
            "price": "37,000(đ)",
            "total_orders": "17020"
        },
        {
            "name": "Trà sữa hạt phỉ (S)",
            "price": "40,000(đ)",
            "total_orders": "14446"
        },
        {
            "name": "Hồng trà sữa (S)",
            "price": "37,000(đ)",
            "total_orders": "11958"
        },
        {
            "name": "Lục trà sữa mật ong (S)",
            "price": "40,000(đ)",
            "total_orders": "11919"
        },
        {
            "name": "Hồng trà sữa (M)",
            "price": "52,000(đ)",
            "total_orders": "10110"
        },
        {
            "name": "Trà sữa caramel (S)",
            "price": "40,000(đ)",
            "total_orders": "6409"
        },
        {
            "name": "Trà sữa cacao (S)",
            "price": "40,000(đ)",
            "total_orders": "4797"
        },
        {
            "name": "Lục trà sữa (M)",
            "price": "52,000(đ)",
            "total_orders": "4791"
        },
        {
            "name": "Trà sữa hạt phỉ (M)",
            "price": "56,000(đ)",
            "total_orders": "4296"
        },
        {
            "name": "Lục trà sữa mật ong (M)",
            "price": "56,000(đ)",
            "total_orders": "4120"
        },
        {
            "name": "Trà sữa caramel (M)",
            "price": "56,000(đ)",
            "total_orders": "2444"
        },
        {
            "name": "Trà sữa cacao (M)",
            "price": "56,000(đ)",
            "total_orders": "1716"
        },
        {
            "name": "Trà sữa trân châu hoàng kim (S)",
            "price": "42,000(đ)",
            "total_orders": "17868"
        },
        {
            "name": "Trà sữa trân châu hoàng kim (M)",
            "price": "59,000(đ)",
            "total_orders": "13748"
        },
        {
            "name": "Trà sữa sương sáo (S)",
            "price": "45,000(đ)",
            "total_orders": "50"
        },
        {
            "name": "Trà sữa sương sáo (M)",
            "price": "63,000(đ)",
            "total_orders": "49"
        },
        {
            "name": "Trà sữa Konjac (S)",
            "price": "48,000(đ)",
            "total_orders": "35"
        },
        {
            "name": "Hồng trà trân châu (S)",
            "price": "34,000(đ)",
            "total_orders": "34"
        },
        {
            "name": "Trà sữa Konjac (M)",
            "price": "68,000(đ)",
            "total_orders": "32"
        },
        {
            "name": "Hồng trà trân châu (M)",
            "price": "48,000(đ)",
            "total_orders": "20"
        },
        {
            "name": "Lô hội chanh dây (S)",
            "price": "45,000(đ)",
            "total_orders": "14"
        },
        {
            "name": "Lục trà trân châu (M)",
            "price": "48,000(đ)",
            "total_orders": "10"
        },
        {
            "name": "Lô hội chanh dây (M)",
            "price": "63,000(đ)",
            "total_orders": "6"
        },
        {
            "name": "Lục trà trân châu (S)",
            "price": "34,000(đ)",
            "total_orders": "6"
        }
    ],
    "user_comments": [
        {
            "user": "Bảo Uyên",
            "link": "https://www.foody.vn/thanh-vien/jennyluke165",
            "score": "7.6",
            "comment": "Không gian: rộng, có lầu, view đẹpChất lượng: đến với koi thì mình thích nhất là blacktea machiato và trà sữa hoàng kim. Hôm nay lần đầu mình thử matcha machiato thì nói thật mình hơi thất vọng, matcha không đậm vị dù mình đã kêu ít đường. Quyết định sẽ trung thành với blacktea machiato thoai😂😂Ấn tượng nhất là câu chào của koi🤣🤣"
        },
        {
            "user": "Love Foods",
            "link": "https://www.foody.vn/thanh-vien/phuongposs",
            "score": "8.0",
            "comment": "Không biết sao nhưng 2 thứ này kết hợp với nhau và khoảng 70% đường thôi đối với mình là hoàn hảo. Macchiato ở Koi khá ngon nhưng uống nhiều thì hơi ngán. Không gian ở Saigon garden rộng tuy nhiên ồn vì cách âm kém. Không thích chỗ gởi xe ở bên đường, hơi bất tiện. Sáng mình ngồi trên lầu chỉ có 3 bàn thôi nhưng âm thanh cứ vang dội rất khó chịu. Nhân viên thân thiện, dễ thương."
        },
        {
            "user": "Trần Nhung",
            "link": "https://www.foody.vn/thanh-vien/tranngochongnhung",
            "score": "6.8",
            "comment": "Lần thứ 2 ghé Koi, vẫn cảm thấy không hợp với mình lắm.Blacktea macchiato đường đá bình thường khá ngọt, vì lớp milkfoam vốn đã ngọt rồi.Matcha latte thì vị matcha đậm, mà chỉ có vậy thôi à, mình không thấy đặc sắc lắm.Không gian thì rộng rãi và dễ thương, nhân viên cũng dễ chịu."
        },
        {
            "user": "Thanh Bình Nguyễn",
            "link": "https://www.foody.vn/thanh-vien/thhhbng",
            "score": "8.8",
            "comment": "Cực thích foam Macchiato ở Koii, vừa đúng với khẩu vị của mình."
        },
        {
            "user": "Yên Yênn",
            "link": "https://www.foody.vn/thanh-vien/b3k3pn0",
            "score": "7.0",
            "comment": "Koi thì khỏi bàn rồi, mình gọi nó là thức uống hạnh phúc, rất đáng đồng tiền và rất giúp cải thiện cảm xúc ( ít nhất là đối với mình), uống ly Koi thay bữa chính cũng đc ý chứ vì thạch luôn đầy ắp ăn no nê cực."
        }
    ]
}
